salic_receipt-0.0.4.dist-info/METADATA
salic_receipt-0.0.4.dist-info/RECORD
salic_receipt-0.0.4.dist-info/WHEEL
salic_receipt-0.0.4.dist-info/entry_points.txt
salic_receipt-0.0.4.dist-info/top_level.txt
salicreceipt/__init__.py
salicreceipt/paths.py
salicreceipt/bin/__init__.py
salicreceipt/bin/download_receipts.py
salicreceipt/data/__init__.py
salicreceipt/data/pickle/__init__.py
salicreceipt/data/pickle/id_arquivos.pickle
