Metadata-Version: 2.1
Name: salic-receipt
Version: 0.0.4
Summary: Download Salic receipt files
Home-page: https://github.com/LucianoPC/salic-receipt
Author: Luciano Prestes Cavalcanti
Author-email: lucianopcbr@gmail.com
License: MIT
Platform: UNKNOWN
Requires-Python: >=3
Requires-Dist: click
Requires-Dist: requests
